pyATC-1.0.6.dist-info/LICENSE.txt
pyATC-1.0.6.dist-info/METADATA
pyATC-1.0.6.dist-info/RECORD
pyATC-1.0.6.dist-info/WHEEL
pyATC-1.0.6.dist-info/top_level.txt
pyatc/__init__.py
pyatc/pyatc.py
pyatc/test.py
