Metadata-Version: 2.1
Name: pyATC
Version: 1.0.6
Summary: Library for working with Alivecor ATC files
Home-page: https://github.com/Thiele/pyatc/
Author: Andreas Thiele
Author-email: andreasthiele@outlook.com
License: MIT
Project-URL: Bug Reports, https://github.com/Thiele/pyatc/issues
Keywords: ATC alivecor edf json
Platform: UNKNOWN
Classifier: Development Status :: 5 - Production/Stable
Classifier: Intended Audience :: Developers
Classifier: Programming Language :: Python :: 2
Classifier: Programming Language :: Python :: 3
Requires-Dist: python-dateutil
